pharmacy/__init__.py
pharmacy/__main__.py
pharmacy/fuzzyjoin/__init__.py
pharmacy-0.4.9.dist-info/LICENSE.txt
pharmacy-0.4.9.dist-info/METADATA
pharmacy-0.4.9.dist-info/WHEEL
pharmacy-0.4.9.dist-info/RECORD
