Metadata-Version: 2.1
Name: pharmacy
Version: 0.4.9
Summary: A set of utilities for use with hospital and retail pharmacy data to deal with common pharmacy operations problems.
License: AGPL-3.0-or-later
Author: Danny Limoges
Author-email: drlimoges@gmail.com
Requires-Python: >=3.10,<4.0
Classifier: Development Status :: 1 - Planning
Classifier: Intended Audience :: Healthcare Industry
Classifier: Intended Audience :: Science/Research
Classifier: License :: OSI Approved :: GNU Affero General Public License v3 or later (AGPLv3+)
Classifier: Natural Language :: English
Classifier: Programming Language :: Python :: 3
Classifier: Programming Language :: Python :: 3.10
Classifier: Programming Language :: Python :: 3.11
Classifier: Topic :: Scientific/Engineering :: Information Analysis
Classifier: Topic :: Scientific/Engineering :: Medical Science Apps.
Classifier: Topic :: Software Development :: Build Tools
Classifier: Topic :: Software Development :: Libraries :: Python Modules
Requires-Dist: pandas (>=1.00.0,<2.0.0)
Requires-Dist: thefuzz (>=0.20.0,<0.21.0)
